{
  "portfolio": {
    "portfolio_id": "demo_01",
    "base_currency": "USD",
    "positions": [
      { "instrument_id": "AAPL", "quantity": "100" },
      { "instrument_id": "MSFT", "quantity": "100" }
    ],
    "cash_balances": [
      { "currency": "USD", "amount": "1000.00" }
    ]
  },
  "market_data": {
    "prices": [
      { "instrument_id": "AAPL", "price": "150.00", "currency": "USD" },
      { "instrument_id": "MSFT", "price": "300.00", "currency": "USD" }
    ],
    "fx_rates": []
  },
  "model": {
    "targets": [
      { "instrument_id": "AAPL", "weight": "0.6" },
      { "instrument_id": "MSFT", "weight": "0.4" }
    ]
  },
  "shelf": [
    { "instrument_id": "AAPL", "status": "APPROVED", "asset_class": "EQUITY" },
    { "instrument_id": "MSFT", "status": "APPROVED", "asset_class": "EQUITY" }
  ],
  "options": {
    "include_explanations": true
  }
}